{"2024-02-09-2024-02-09": [[{"color": "orangered", "size": 30, "id": "MEX - Salomón Chertorivski - TW", "label": "MEX - Salomón Chertorivski - TW", "shape": "dot", "font": {"color": "white"}}, {"color": "orangered", "size": 10, "id": "defiende-argumenta", "label": "defiende-argumenta", "shape": "dot", "font": {"color": "white"}}, {"color": "orangered", "size": 10, "id": "argumenta-política", "label": "argumenta-política", "shape": "dot", "font": {"color": "white"}}, {"color": "orangered", "size": 10, "id": "política-señala", "label": "política-señala", "shape": "dot", "font": {"color": "white"}}, {"color": "orangered", "size": 10, "id": "señala-mierrey", "label": "señala-mierrey", "shape": "dot", "font": {"color": "white"}}, {"color": "orangered", "size": 10, "id": "mierrey-gobernador", "label": "mierrey-gobernador", "shape": "dot", "font": {"color": "white"}}, {"color": "orangered", "size": 10, "id": "gobernador-referente", "label": "gobernador-referente", "shape": "dot", "font": {"color": "white"}}, {"color": "orangered", "size": 10, "id": "referente-pregunto", "label": "referente-pregunto", "shape": "dot", "font": {"color": "white"}}, {"color": "orangered", "size": 10, "id": "pregunto-opinión", "label": "pregunto-opinión", "shape": "dot", "font": {"color": "white"}}, {"color": "orangered", "size": 10, "id": "opinión-samuel", "label": "opinión-samuel", "shape": "dot", "font": {"color": "white"}}, {"color": "orangered", "size": 10, "id": "movimiento-caguama", "label": "movimiento-caguama", "shape": "dot", "font": {"color": "white"}}, {"color": "orangered", "size": 10, "id": "verdadera-oposición", "label": "verdadera-oposición", "shape": "dot", "font": {"color": "white"}}, {"color": "#8c6563", "size": 18, "id": "ciudad-méxico", "label": "ciudad-méxico", "shape": "dot", "font": {"color": "white"}}, {"color": "orangered", "size": 10, "id": "salomón-chertorivski", "label": "salomón-chertorivski", "shape": "dot", "font": {"color": "white"}}, {"color": "orangered", "size": 10, "id": "movimiento-ciudadano", "label": "movimiento-ciudadano", "shape": "dot", "font": {"color": "white"}}, {"color": "orangered", "size": 10, "id": "también-compartes", "label": "también-compartes", "shape": "dot", "font": {"color": "white"}}, {"color": "orangered", "size": 10, "id": "defendiendo-indefendible", "label": "defendiendo-indefendible", "shape": "dot", "font": {"color": "white"}}, {"color": "orangered", "size": 10, "id": "mejores-causas", "label": "mejores-causas", "shape": "dot", "font": {"color": "white"}}, {"color": "orangered", "size": 10, "id": "candidatos-alcaldías", "label": "candidatos-alcaldías", "shape": "dot", "font": {"color": "white"}}, {"color": "orangered", "size": 10, "id": "pierdan-registro", "label": "pierdan-registro", "shape": "dot", "font": {"color": "white"}}, {"color": "orangered", "size": 10, "id": "crisis-hídrica", "label": "crisis-hídrica", "shape": "dot", "font": {"color": "white"}}, {"color": "orangered", "size": 10, "id": "declare-emergencia", "label": "declare-emergencia", "shape": "dot", "font": {"color": "white"}}, {"color": "#808280", "size": 14, "id": "jefatura-gobierno", "label": "jefatura-gobierno", "shape": "dot", "font": {"color": "white"}}, {"color": "orangered", "size": 10, "id": "servidor-público", "label": "servidor-público", "shape": "dot", "font": {"color": "white"}}, {"color": "orangered", "size": 10, "id": "perfecto-idiota", "label": "perfecto-idiota", "shape": "dot", "font": {"color": "white"}}, {"color": "orangered", "size": 10, "id": "defendido-mejores", "label": "defendido-mejores", "shape": "dot", "font": {"color": "white"}}, {"color": "orangered", "size": 10, "id": "enorgullece-compartir", "label": "enorgullece-compartir", "shape": "dot", "font": {"color": "white"}}, {"color": "orangered", "size": 10, "id": "compartir-valores", "label": "compartir-valores", "shape": "dot", "font": {"color": "white"}}, {"color": "orangered", "size": 10, "id": "valores-causas", "label": "valores-causas", "shape": "dot", "font": {"color": "white"}}, {"color": "orangered", "size": 10, "id": "define-candidatos", "label": "define-candidatos", "shape": "dot", "font": {"color": "white"}}, {"color": "orangered", "size": 10, "id": "alcaldías-diputaciones", "label": "alcaldías-diputaciones", "shape": "dot", "font": {"color": "white"}}, {"color": "deepskyblue", "size": 30, "id": "MEX - Santiago Taboada - TW", "label": "MEX - Santiago Taboada - TW", "shape": "dot", "font": {"color": "white"}}, {"color": "#527494", "size": 14, "id": "cartel-inmobiliario", "label": "cartel-inmobiliario", "shape": "dot", "font": {"color": "white"}}, {"color": "deepskyblue", "size": 10, "id": "santiago-taboada", "label": "santiago-taboada", "shape": "dot", "font": {"color": "white"}}, {"color": "#527494", "size": 14, "id": "benito-juárez", "label": "benito-juárez", "shape": "dot", "font": {"color": "white"}}, {"color": "deepskyblue", "size": 10, "id": "cártel-inmobiliario", "label": "cártel-inmobiliario", "shape": "dot", "font": {"color": "white"}}, {"color": "deepskyblue", "size": 10, "id": "estados-unidos", "label": "estados-unidos", "shape": "dot", "font": {"color": "white"}}, {"color": "deepskyblue", "size": 10, "id": "alcaldía-benito", "label": "alcaldía-benito", "shape": "dot", "font": {"color": "white"}}, {"color": "deepskyblue", "size": 10, "id": "recibiendo-mensajes", "label": "recibiendo-mensajes", "shape": "dot", "font": {"color": "white"}}, {"color": "deepskyblue", "size": 10, "id": "xóchitl-gálvez", "label": "xóchitl-gálvez", "shape": "dot", "font": {"color": "white"}}, {"color": "deepskyblue", "size": 10, "id": "persecución-política", "label": "persecución-política", "shape": "dot", "font": {"color": "white"}}, {"color": "deepskyblue", "size": 10, "id": "jajajaja-jajajaja", "label": "jajajaja-jajajaja", "shape": "dot", "font": {"color": "white"}}, {"color": "deepskyblue", "size": 10, "id": "mensajes-vecinos", "label": "mensajes-vecinos", "shape": "dot", "font": {"color": "white"}}, {"color": "deepskyblue", "size": 10, "id": "corrupción-inmobiliaria", "label": "corrupción-inmobiliaria", "shape": "dot", "font": {"color": "white"}}, {"color": "deepskyblue", "size": 10, "id": "nuestra-democracia", "label": "nuestra-democracia", "shape": "dot", "font": {"color": "white"}}, {"color": "deepskyblue", "size": 10, "id": "defender-democracia", "label": "defender-democracia", "shape": "dot", "font": {"color": "white"}}, {"color": "deepskyblue", "size": 10, "id": "jornada-ciudadana", "label": "jornada-ciudadana", "shape": "dot", "font": {"color": "white"}}, {"color": "deepskyblue", "size": 10, "id": "democracia-domingo", "label": "democracia-domingo", "shape": "dot", "font": {"color": "white"}}, {"color": "deepskyblue", "size": 10, "id": "domingo-ubicación", "label": "domingo-ubicación", "shape": "dot", "font": {"color": "white"}}, {"color": "deepskyblue", "size": 10, "id": "ubicación-cercana", "label": "ubicación-cercana", "shape": "dot", "font": {"color": "white"}}, {"color": "deepskyblue", "size": 10, "id": "próximo-gobierno", "label": "próximo-gobierno", "shape": "dot", "font": {"color": "white"}}, {"color": "deepskyblue", "size": 10, "id": "elección-estado", "label": "elección-estado", "shape": "dot", "font": {"color": "white"}}, {"color": "deepskyblue", "size": 10, "id": "porque-subterráneo", "label": "porque-subterráneo", "shape": "dot", "font": {"color": "white"}}, {"color": "deepskyblue", "size": 10, "id": "transporte-público", "label": "transporte-público", "shape": "dot", "font": {"color": "white"}}, {"color": "deepskyblue", "size": 10, "id": "inmobiliario-porque", "label": "inmobiliario-porque", "shape": "dot", "font": {"color": "white"}}, {"color": "deepskyblue", "size": 10, "id": "estamos-contigo", "label": "estamos-contigo", "shape": "dot", "font": {"color": "white"}}, {"color": "deepskyblue", "size": 10, "id": "alcaldía-segura", "label": "alcaldía-segura", "shape": "dot", "font": {"color": "white"}}, {"color": "deepskyblue", "size": 10, "id": "traidores-patria", "label": "traidores-patria", "shape": "dot", "font": {"color": "white"}}, {"color": "deepskyblue", "size": 10, "id": "taboada-cartel", "label": "taboada-cartel", "shape": "dot", "font": {"color": "white"}}, {"color": "deepskyblue", "size": 10, "id": "defensa-nuestra", "label": "defensa-nuestra", "shape": "dot", "font": {"color": "white"}}, {"color": "brown", "size": 30, "id": "MEX - Clara Brugada - TW", "label": "MEX - Clara Brugada - TW", "shape": "dot", "font": {"color": "white"}}, {"color": "brown", "size": 10, "id": "crimen-organizado", "label": "crimen-organizado", "shape": "dot", "font": {"color": "white"}}, {"color": "brown", "size": 10, "id": "narcos-felicidad", "label": "narcos-felicidad", "shape": "dot", "font": {"color": "white"}}, {"color": "brown", "size": 10, "id": "felicidad-verdad", "label": "felicidad-verdad", "shape": "dot", "font": {"color": "white"}}, {"color": "brown", "size": 10, "id": "verdad-empiece", "label": "verdad-empiece", "shape": "dot", "font": {"color": "white"}}, {"color": "brown", "size": 10, "id": "empiece-conocer", "label": "empiece-conocer", "shape": "dot", "font": {"color": "white"}}, {"color": "brown", "size": 10, "id": "conocer-popular", "label": "conocer-popular", "shape": "dot", "font": {"color": "white"}}, {"color": "brown", "size": 10, "id": "popular-crimen", "label": "popular-crimen", "shape": "dot", "font": {"color": "white"}}, {"color": "brown", "size": 10, "id": "organizado-narcos", "label": "organizado-narcos", "shape": "dot", "font": {"color": "white"}}, {"color": "brown", "size": 10, "id": "magdalena-contreras", "label": "magdalena-contreras", "shape": "dot", "font": {"color": "white"}}, {"color": "brown", "size": 10, "id": "morena-huerta", "label": "morena-huerta", "shape": "dot", "font": {"color": "white"}}, {"color": "brown", "size": 10, "id": "claudia-sheinbaum", "label": "claudia-sheinbaum", "shape": "dot", "font": {"color": "white"}}, {"color": "brown", "size": 10, "id": "gustavo-mendoza", "label": "gustavo-mendoza", "shape": "dot", "font": {"color": "white"}}, {"color": "brown", "size": 10, "id": "fiscalía-proceso", "label": "fiscalía-proceso", "shape": "dot", "font": {"color": "white"}}, {"color": "brown", "size": 10, "id": "proceso-exdiputado", "label": "proceso-exdiputado", "shape": "dot", "font": {"color": "white"}}, {"color": "brown", "size": 10, "id": "exdiputado-morena", "label": "exdiputado-morena", "shape": "dot", "font": {"color": "white"}}, {"color": "brown", "size": 10, "id": "huerta-llevado", "label": "huerta-llevado", "shape": "dot", "font": {"color": "white"}}, {"color": "brown", "size": 10, "id": "llevado-sentencia", "label": "llevado-sentencia", "shape": "dot", "font": {"color": "white"}}, {"color": "brown", "size": 10, "id": "viviendo-erario", "label": "viviendo-erario", "shape": "dot", "font": {"color": "white"}}, {"color": "brown", "size": 10, "id": "gobierno-izquierda", "label": "gobierno-izquierda", "shape": "dot", "font": {"color": "white"}}, {"color": "brown", "size": 10, "id": "presidente-andrés", "label": "presidente-andrés", "shape": "dot", "font": {"color": "white"}}, {"color": "brown", "size": 10, "id": "andrés-manuel", "label": "andrés-manuel", "shape": "dot", "font": {"color": "white"}}, {"color": "brown", "size": 10, "id": "manuel-obrador", "label": "manuel-obrador", "shape": "dot", "font": {"color": "white"}}, {"color": "brown", "size": 10, "id": "sheinbaum-brugada", "label": "sheinbaum-brugada", "shape": "dot", "font": {"color": "white"}}, {"color": "brown", "size": 10, "id": "fernando-mercado", "label": "fernando-mercado", "shape": "dot", "font": {"color": "white"}}, {"color": "brown", "size": 10, "id": "grandes-mujeres", "label": "grandes-mujeres", "shape": "dot", "font": {"color": "white"}}, {"color": "brown", "size": 10, "id": "obrador-doctora", "label": "obrador-doctora", "shape": "dot", "font": {"color": "white"}}, {"color": "brown", "size": 10, "id": "doctora-claudia", "label": "doctora-claudia", "shape": "dot", "font": {"color": "white"}}], [{"Frecuencia": 8, "value": 0.07407407407407407, "width": 0.07407407407407407, "length": 13.5, "from": "MEX - Salomón Chertorivski - TW", "to": "defiende-argumenta"}, {"Frecuencia": 8, "value": 0.07407407407407407, "width": 0.07407407407407407, "length": 13.5, "from": "MEX - Salomón Chertorivski - TW", "to": "argumenta-política"}, {"Frecuencia": 8, "value": 0.07407407407407407, "width": 0.07407407407407407, "length": 13.5, "from": "MEX - Salomón Chertorivski - TW", "to": "política-señala"}, {"Frecuencia": 8, "value": 0.07407407407407407, "width": 0.07407407407407407, "length": 13.5, "from": "MEX - Salomón Chertorivski - TW", "to": "señala-mierrey"}, {"Frecuencia": 8, "value": 0.07407407407407407, "width": 0.07407407407407407, "length": 13.5, "from": "MEX - Salomón Chertorivski - TW", "to": "mierrey-gobernador"}, {"Frecuencia": 8, "value": 0.07407407407407407, "width": 0.07407407407407407, "length": 13.5, "from": "MEX - Salomón Chertorivski - TW", "to": "gobernador-referente"}, {"Frecuencia": 8, "value": 0.07407407407407407, "width": 0.07407407407407407, "length": 13.5, "from": "MEX - Salomón Chertorivski - TW", "to": "referente-pregunto"}, {"Frecuencia": 8, "value": 0.07407407407407407, "width": 0.07407407407407407, "length": 13.5, "from": "MEX - Salomón Chertorivski - TW", "to": "pregunto-opinión"}, {"Frecuencia": 8, "value": 0.07407407407407407, "width": 0.07407407407407407, "length": 13.5, "from": "MEX - Salomón Chertorivski - TW", "to": "opinión-samuel"}, {"Frecuencia": 6, "value": 0.05555555555555555, "width": 0.05555555555555555, "length": 18.0, "from": "MEX - Salomón Chertorivski - TW", "to": "movimiento-caguama"}, {"Frecuencia": 6, "value": 0.05555555555555555, "width": 0.05555555555555555, "length": 18.0, "from": "MEX - Salomón Chertorivski - TW", "to": "verdadera-oposición"}, {"Frecuencia": 5, "value": 0.046296296296296294, "width": 0.046296296296296294, "length": 21.6, "from": "MEX - Salomón Chertorivski - TW", "to": "ciudad-méxico"}, {"Frecuencia": 4, "value": 0.037037037037037035, "width": 0.037037037037037035, "length": 27.0, "from": "MEX - Salomón Chertorivski - TW", "to": "salomón-chertorivski"}, {"Frecuencia": 4, "value": 0.037037037037037035, "width": 0.037037037037037035, "length": 27.0, "from": "MEX - Salomón Chertorivski - TW", "to": "movimiento-ciudadano"}, {"Frecuencia": 4, "value": 0.037037037037037035, "width": 0.037037037037037035, "length": 27.0, "from": "MEX - Salomón Chertorivski - TW", "to": "también-compartes"}, {"Frecuencia": 4, "value": 0.037037037037037035, "width": 0.037037037037037035, "length": 27.0, "from": "MEX - Salomón Chertorivski - TW", "to": "defendiendo-indefendible"}, {"Frecuencia": 3, "value": 0.027777777777777776, "width": 0.027777777777777776, "length": 36.0, "from": "MEX - Salomón Chertorivski - TW", "to": "mejores-causas"}, {"Frecuencia": 3, "value": 0.027777777777777776, "width": 0.027777777777777776, "length": 36.0, "from": "MEX - Salomón Chertorivski - TW", "to": "candidatos-alcaldías"}, {"Frecuencia": 3, "value": 0.027777777777777776, "width": 0.027777777777777776, "length": 36.0, "from": "MEX - Salomón Chertorivski - TW", "to": "pierdan-registro"}, {"Frecuencia": 3, "value": 0.027777777777777776, "width": 0.027777777777777776, "length": 36.0, "from": "MEX - Salomón Chertorivski - TW", "to": "crisis-hídrica"}, {"Frecuencia": 3, "value": 0.027777777777777776, "width": 0.027777777777777776, "length": 36.0, "from": "MEX - Salomón Chertorivski - TW", "to": "declare-emergencia"}, {"Frecuencia": 3, "value": 0.027777777777777776, "width": 0.027777777777777776, "length": 36.0, "from": "MEX - Salomón Chertorivski - TW", "to": "jefatura-gobierno"}, {"Frecuencia": 3, "value": 0.027777777777777776, "width": 0.027777777777777776, "length": 36.0, "from": "MEX - Salomón Chertorivski - TW", "to": "servidor-público"}, {"Frecuencia": 3, "value": 0.027777777777777776, "width": 0.027777777777777776, "length": 36.0, "from": "MEX - Salomón Chertorivski - TW", "to": "perfecto-idiota"}, {"Frecuencia": 2, "value": 0.018518518518518517, "width": 0.018518518518518517, "length": 54.0, "from": "MEX - Salomón Chertorivski - TW", "to": "defendido-mejores"}, {"Frecuencia": 2, "value": 0.018518518518518517, "width": 0.018518518518518517, "length": 54.0, "from": "MEX - Salomón Chertorivski - TW", "to": "enorgullece-compartir"}, {"Frecuencia": 2, "value": 0.018518518518518517, "width": 0.018518518518518517, "length": 54.0, "from": "MEX - Salomón Chertorivski - TW", "to": "compartir-valores"}, {"Frecuencia": 2, "value": 0.018518518518518517, "width": 0.018518518518518517, "length": 54.0, "from": "MEX - Salomón Chertorivski - TW", "to": "valores-causas"}, {"Frecuencia": 2, "value": 0.018518518518518517, "width": 0.018518518518518517, "length": 54.0, "from": "MEX - Salomón Chertorivski - TW", "to": "define-candidatos"}, {"Frecuencia": 2, "value": 0.018518518518518517, "width": 0.018518518518518517, "length": 54.0, "from": "MEX - Salomón Chertorivski - TW", "to": "alcaldías-diputaciones"}, {"Frecuencia": 22, "value": 0.2037037037037037, "width": 0.2037037037037037, "length": 4.909090909090909, "from": "ciudad-méxico", "to": "MEX - Santiago Taboada - TW"}, {"Frecuencia": 39, "value": 0.3611111111111111, "width": 0.3611111111111111, "length": 2.769230769230769, "from": "ciudad-méxico", "to": "MEX - Clara Brugada - TW"}, {"Frecuencia": 9, "value": 0.08333333333333333, "width": 0.08333333333333333, "length": 12.0, "from": "jefatura-gobierno", "to": "MEX - Santiago Taboada - TW"}, {"Frecuencia": 108, "value": 1.0, "width": 1.0, "length": 1.0, "from": "MEX - Santiago Taboada - TW", "to": "cartel-inmobiliario"}, {"Frecuencia": 46, "value": 0.42592592592592593, "width": 0.42592592592592593, "length": 2.3478260869565215, "from": "MEX - Santiago Taboada - TW", "to": "santiago-taboada"}, {"Frecuencia": 39, "value": 0.3611111111111111, "width": 0.3611111111111111, "length": 2.769230769230769, "from": "MEX - Santiago Taboada - TW", "to": "benito-juárez"}, {"Frecuencia": 32, "value": 0.2962962962962963, "width": 0.2962962962962963, "length": 3.375, "from": "MEX - Santiago Taboada - TW", "to": "cártel-inmobiliario"}, {"Frecuencia": 21, "value": 0.19444444444444445, "width": 0.19444444444444445, "length": 5.142857142857142, "from": "MEX - Santiago Taboada - TW", "to": "estados-unidos"}, {"Frecuencia": 13, "value": 0.12037037037037036, "width": 0.12037037037037036, "length": 8.307692307692308, "from": "MEX - Santiago Taboada - TW", "to": "alcaldía-benito"}, {"Frecuencia": 11, "value": 0.10185185185185185, "width": 0.10185185185185185, "length": 9.818181818181818, "from": "MEX - Santiago Taboada - TW", "to": "recibiendo-mensajes"}, {"Frecuencia": 10, "value": 0.09259259259259259, "width": 0.09259259259259259, "length": 10.8, "from": "MEX - Santiago Taboada - TW", "to": "xóchitl-gálvez"}, {"Frecuencia": 10, "value": 0.09259259259259259, "width": 0.09259259259259259, "length": 10.8, "from": "MEX - Santiago Taboada - TW", "to": "persecución-política"}, {"Frecuencia": 9, "value": 0.08333333333333333, "width": 0.08333333333333333, "length": 12.0, "from": "MEX - Santiago Taboada - TW", "to": "jajajaja-jajajaja"}, {"Frecuencia": 8, "value": 0.07407407407407407, "width": 0.07407407407407407, "length": 13.5, "from": "MEX - Santiago Taboada - TW", "to": "mensajes-vecinos"}, {"Frecuencia": 7, "value": 0.06481481481481481, "width": 0.06481481481481481, "length": 15.428571428571429, "from": "MEX - Santiago Taboada - TW", "to": "corrupción-inmobiliaria"}, {"Frecuencia": 7, "value": 0.06481481481481481, "width": 0.06481481481481481, "length": 15.428571428571429, "from": "MEX - Santiago Taboada - TW", "to": "nuestra-democracia"}, {"Frecuencia": 6, "value": 0.05555555555555555, "width": 0.05555555555555555, "length": 18.0, "from": "MEX - Santiago Taboada - TW", "to": "defender-democracia"}, {"Frecuencia": 6, "value": 0.05555555555555555, "width": 0.05555555555555555, "length": 18.0, "from": "MEX - Santiago Taboada - TW", "to": "jornada-ciudadana"}, {"Frecuencia": 6, "value": 0.05555555555555555, "width": 0.05555555555555555, "length": 18.0, "from": "MEX - Santiago Taboada - TW", "to": "democracia-domingo"}, {"Frecuencia": 6, "value": 0.05555555555555555, "width": 0.05555555555555555, "length": 18.0, "from": "MEX - Santiago Taboada - TW", "to": "domingo-ubicación"}, {"Frecuencia": 6, "value": 0.05555555555555555, "width": 0.05555555555555555, "length": 18.0, "from": "MEX - Santiago Taboada - TW", "to": "ubicación-cercana"}, {"Frecuencia": 6, "value": 0.05555555555555555, "width": 0.05555555555555555, "length": 18.0, "from": "MEX - Santiago Taboada - TW", "to": "próximo-gobierno"}, {"Frecuencia": 6, "value": 0.05555555555555555, "width": 0.05555555555555555, "length": 18.0, "from": "MEX - Santiago Taboada - TW", "to": "elección-estado"}, {"Frecuencia": 6, "value": 0.05555555555555555, "width": 0.05555555555555555, "length": 18.0, "from": "MEX - Santiago Taboada - TW", "to": "porque-subterráneo"}, {"Frecuencia": 6, "value": 0.05555555555555555, "width": 0.05555555555555555, "length": 18.0, "from": "MEX - Santiago Taboada - TW", "to": "transporte-público"}, {"Frecuencia": 6, "value": 0.05555555555555555, "width": 0.05555555555555555, "length": 18.0, "from": "MEX - Santiago Taboada - TW", "to": "inmobiliario-porque"}, {"Frecuencia": 5, "value": 0.046296296296296294, "width": 0.046296296296296294, "length": 21.6, "from": "MEX - Santiago Taboada - TW", "to": "estamos-contigo"}, {"Frecuencia": 5, "value": 0.046296296296296294, "width": 0.046296296296296294, "length": 21.6, "from": "MEX - Santiago Taboada - TW", "to": "alcaldía-segura"}, {"Frecuencia": 5, "value": 0.046296296296296294, "width": 0.046296296296296294, "length": 21.6, "from": "MEX - Santiago Taboada - TW", "to": "traidores-patria"}, {"Frecuencia": 5, "value": 0.046296296296296294, "width": 0.046296296296296294, "length": 21.6, "from": "MEX - Santiago Taboada - TW", "to": "taboada-cartel"}, {"Frecuencia": 4, "value": 0.037037037037037035, "width": 0.037037037037037035, "length": 27.0, "from": "MEX - Santiago Taboada - TW", "to": "defensa-nuestra"}, {"Frecuencia": 6, "value": 0.05555555555555555, "width": 0.05555555555555555, "length": 18.0, "from": "cartel-inmobiliario", "to": "MEX - Clara Brugada - TW"}, {"Frecuencia": 13, "value": 0.12037037037037036, "width": 0.12037037037037036, "length": 8.307692307692308, "from": "benito-juárez", "to": "MEX - Clara Brugada - TW"}, {"Frecuencia": 43, "value": 0.39814814814814814, "width": 0.39814814814814814, "length": 2.511627906976744, "from": "MEX - Clara Brugada - TW", "to": "crimen-organizado"}, {"Frecuencia": 42, "value": 0.3888888888888889, "width": 0.3888888888888889, "length": 2.571428571428571, "from": "MEX - Clara Brugada - TW", "to": "narcos-felicidad"}, {"Frecuencia": 42, "value": 0.3888888888888889, "width": 0.3888888888888889, "length": 2.571428571428571, "from": "MEX - Clara Brugada - TW", "to": "felicidad-verdad"}, {"Frecuencia": 42, "value": 0.3888888888888889, "width": 0.3888888888888889, "length": 2.571428571428571, "from": "MEX - Clara Brugada - TW", "to": "verdad-empiece"}, {"Frecuencia": 42, "value": 0.3888888888888889, "width": 0.3888888888888889, "length": 2.571428571428571, "from": "MEX - Clara Brugada - TW", "to": "empiece-conocer"}, {"Frecuencia": 42, "value": 0.3888888888888889, "width": 0.3888888888888889, "length": 2.571428571428571, "from": "MEX - Clara Brugada - TW", "to": "conocer-popular"}, {"Frecuencia": 42, "value": 0.3888888888888889, "width": 0.3888888888888889, "length": 2.571428571428571, "from": "MEX - Clara Brugada - TW", "to": "popular-crimen"}, {"Frecuencia": 22, "value": 0.2037037037037037, "width": 0.2037037037037037, "length": 4.909090909090909, "from": "MEX - Clara Brugada - TW", "to": "organizado-narcos"}, {"Frecuencia": 14, "value": 0.12962962962962962, "width": 0.12962962962962962, "length": 7.714285714285714, "from": "MEX - Clara Brugada - TW", "to": "magdalena-contreras"}, {"Frecuencia": 12, "value": 0.1111111111111111, "width": 0.1111111111111111, "length": 9.0, "from": "MEX - Clara Brugada - TW", "to": "morena-huerta"}, {"Frecuencia": 11, "value": 0.10185185185185185, "width": 0.10185185185185185, "length": 9.818181818181818, "from": "MEX - Clara Brugada - TW", "to": "claudia-sheinbaum"}, {"Frecuencia": 10, "value": 0.09259259259259259, "width": 0.09259259259259259, "length": 10.8, "from": "MEX - Clara Brugada - TW", "to": "gustavo-mendoza"}, {"Frecuencia": 9, "value": 0.08333333333333333, "width": 0.08333333333333333, "length": 12.0, "from": "MEX - Clara Brugada - TW", "to": "fiscalía-proceso"}, {"Frecuencia": 9, "value": 0.08333333333333333, "width": 0.08333333333333333, "length": 12.0, "from": "MEX - Clara Brugada - TW", "to": "proceso-exdiputado"}, {"Frecuencia": 9, "value": 0.08333333333333333, "width": 0.08333333333333333, "length": 12.0, "from": "MEX - Clara Brugada - TW", "to": "exdiputado-morena"}, {"Frecuencia": 9, "value": 0.08333333333333333, "width": 0.08333333333333333, "length": 12.0, "from": "MEX - Clara Brugada - TW", "to": "huerta-llevado"}, {"Frecuencia": 9, "value": 0.08333333333333333, "width": 0.08333333333333333, "length": 12.0, "from": "MEX - Clara Brugada - TW", "to": "llevado-sentencia"}, {"Frecuencia": 7, "value": 0.06481481481481481, "width": 0.06481481481481481, "length": 15.428571428571429, "from": "MEX - Clara Brugada - TW", "to": "viviendo-erario"}, {"Frecuencia": 7, "value": 0.06481481481481481, "width": 0.06481481481481481, "length": 15.428571428571429, "from": "MEX - Clara Brugada - TW", "to": "gobierno-izquierda"}, {"Frecuencia": 7, "value": 0.06481481481481481, "width": 0.06481481481481481, "length": 15.428571428571429, "from": "MEX - Clara Brugada - TW", "to": "presidente-andrés"}, {"Frecuencia": 7, "value": 0.06481481481481481, "width": 0.06481481481481481, "length": 15.428571428571429, "from": "MEX - Clara Brugada - TW", "to": "andrés-manuel"}, {"Frecuencia": 7, "value": 0.06481481481481481, "width": 0.06481481481481481, "length": 15.428571428571429, "from": "MEX - Clara Brugada - TW", "to": "manuel-obrador"}, {"Frecuencia": 7, "value": 0.06481481481481481, "width": 0.06481481481481481, "length": 15.428571428571429, "from": "MEX - Clara Brugada - TW", "to": "sheinbaum-brugada"}, {"Frecuencia": 7, "value": 0.06481481481481481, "width": 0.06481481481481481, "length": 15.428571428571429, "from": "MEX - Clara Brugada - TW", "to": "fernando-mercado"}, {"Frecuencia": 6, "value": 0.05555555555555555, "width": 0.05555555555555555, "length": 18.0, "from": "MEX - Clara Brugada - TW", "to": "grandes-mujeres"}, {"Frecuencia": 6, "value": 0.05555555555555555, "width": 0.05555555555555555, "length": 18.0, "from": "MEX - Clara Brugada - TW", "to": "obrador-doctora"}, {"Frecuencia": 6, "value": 0.05555555555555555, "width": 0.05555555555555555, "length": 18.0, "from": "MEX - Clara Brugada - TW", "to": "doctora-claudia"}]], "2024-02-08-2024-02-08": [[{"color": "orangered", "size": 30, "id": "MEX - Salomón Chertorivski - TW", "label": "MEX - Salomón Chertorivski - TW", "shape": "dot", "font": {"color": "white"}}, {"color": "orangered", "size": 10, "id": "movimiento-ciudadano", "label": "movimiento-ciudadano", "shape": "dot", "font": {"color": "white"}}, {"color": "#8c6563", "size": 18, "id": "ciudad-méxico", "label": "ciudad-méxico", "shape": "dot", "font": {"color": "white"}}, {"color": "orangered", "size": 10, "id": "repetición-programa", "label": "repetición-programa", "shape": "dot", "font": {"color": "white"}}, {"color": "orangered", "size": 10, "id": "programa-análisis", "label": "programa-análisis", "shape": "dot", "font": {"color": "white"}}, {"color": "orangered", "size": 10, "id": "análisis-colaboradores", "label": "análisis-colaboradores", "shape": "dot", "font": {"color": "white"}}, {"color": "orangered", "size": 10, "id": "candidato-salomón", "label": "candidato-salomón", "shape": "dot", "font": {"color": "white"}}, {"color": "orangered", "size": 10, "id": "emergencia-hídrica", "label": "emergencia-hídrica", "shape": "dot", "font": {"color": "white"}}, {"color": "#8c6563", "size": 18, "id": "cartel-inmobiliario", "label": "cartel-inmobiliario", "shape": "dot", "font": {"color": "white"}}, {"color": "orangered", "size": 10, "id": "continúa-horario", "label": "continúa-horario", "shape": "dot", "font": {"color": "white"}}, {"color": "orangered", "size": 10, "id": "horario-repetición", "label": "horario-repetición", "shape": "dot", "font": {"color": "white"}}, {"color": "orangered", "size": 10, "id": "colaboradores-entrevistará", "label": "colaboradores-entrevistará", "shape": "dot", "font": {"color": "white"}}, {"color": "orangered", "size": 10, "id": "entrevistará-candidato", "label": "entrevistará-candidato", "shape": "dot", "font": {"color": "white"}}, {"color": "#8c6563", "size": 18, "id": "jefatura-gobierno", "label": "jefatura-gobierno", "shape": "dot", "font": {"color": "white"}}, {"color": "orangered", "size": 10, "id": "salomón-partido", "label": "salomón-partido", "shape": "dot", "font": {"color": "white"}}, {"color": "orangered", "size": 10, "id": "declare-emergencia", "label": "declare-emergencia", "shape": "dot", "font": {"color": "white"}}, {"color": "orangered", "size": 10, "id": "muchas-gracias", "label": "muchas-gracias", "shape": "dot", "font": {"color": "white"}}, {"color": "orangered", "size": 10, "id": "boletos-cuenta", "label": "boletos-cuenta", "shape": "dot", "font": {"color": "white"}}, {"color": "orangered", "size": 10, "id": "cuenta-cualquier", "label": "cuenta-cualquier", "shape": "dot", "font": {"color": "white"}}, {"color": "orangered", "size": 10, "id": "cualquier-evento", "label": "cualquier-evento", "shape": "dot", "font": {"color": "white"}}, {"color": "orangered", "size": 10, "id": "evento-falsos", "label": "evento-falsos", "shape": "dot", "font": {"color": "white"}}, {"color": "orangered", "size": 10, "id": "falsos-trabaja", "label": "falsos-trabaja", "shape": "dot", "font": {"color": "white"}}, {"color": "orangered", "size": 10, "id": "trabaja-estudio", "label": "trabaja-estudio", "shape": "dot", "font": {"color": "white"}}, {"color": "orangered", "size": 10, "id": "estudio-ratero", "label": "estudio-ratero", "shape": "dot", "font": {"color": "white"}}, {"color": "orangered", "size": 10, "id": "ratero-estafador", "label": "ratero-estafador", "shape": "dot", "font": {"color": "white"}}, {"color": "orangered", "size": 10, "id": "estafador-falsas", "label": "estafador-falsas", "shape": "dot", "font": {"color": "white"}}, {"color": "orangered", "size": 10, "id": "chertorivski-advierte", "label": "chertorivski-advierte", "shape": "dot", "font": {"color": "white"}}, {"color": "orangered", "size": 10, "id": "advierte-crisis", "label": "advierte-crisis", "shape": "dot", "font": {"color": "white"}}, {"color": "orangered", "size": 10, "id": "tenemos-paliza", "label": "tenemos-paliza", "shape": "dot", "font": {"color": "white"}}, {"color": "orangered", "size": 10, "id": "paliza-exterminar", "label": "paliza-exterminar", "shape": "dot", "font": {"color": "white"}}, {"color": "orangered", "size": 10, "id": "exterminar-exterminando", "label": "exterminar-exterminando", "shape": "dot", "font": {"color": "white"}}, {"color": "deepskyblue", "size": 30, "id": "MEX - Santiago Taboada - TW", "label": "MEX - Santiago Taboada - TW", "shape": "dot", "font": {"color": "white"}}, {"color": "#527494", "size": 14, "id": "santiago-taboada", "label": "santiago-taboada", "shape": "dot", "font": {"color": "white"}}, {"color": "deepskyblue", "size": 10, "id": "persecución-política", "label": "persecución-política", "shape": "dot", "font": {"color": "white"}}, {"color": "#527494", "size": 14, "id": "cártel-inmobiliario", "label": "cártel-inmobiliario", "shape": "dot", "font": {"color": "white"}}, {"color": "#527494", "size": 14, "id": "estados-unidos", "label": "estados-unidos", "shape": "dot", "font": {"color": "white"}}, {"color": "deepskyblue", "size": 10, "id": "elección-estado", "label": "elección-estado", "shape": "dot", "font": {"color": "white"}}, {"color": "deepskyblue", "size": 10, "id": "traidores-patria", "label": "traidores-patria", "shape": "dot", "font": {"color": "white"}}, {"color": "#527494", "size": 14, "id": "benito-juárez", "label": "benito-juárez", "shape": "dot", "font": {"color": "white"}}, {"color": "deepskyblue", "size": 10, "id": "cuello-blanco", "label": "cuello-blanco", "shape": "dot", "font": {"color": "white"}}, {"color": "deepskyblue", "size": 10, "id": "perseguidos-políticos", "label": "perseguidos-políticos", "shape": "dot", "font": {"color": "white"}}, {"color": "deepskyblue", "size": 10, "id": "pueblo-méxico", "label": "pueblo-méxico", "shape": "dot", "font": {"color": "white"}}, {"color": "deepskyblue", "size": 10, "id": "perseguido-político", "label": "perseguido-político", "shape": "dot", "font": {"color": "white"}}, {"color": "deepskyblue", "size": 10, "id": "xóchitl-gálvez", "label": "xóchitl-gálvez", "shape": "dot", "font": {"color": "white"}}, {"color": "deepskyblue", "size": 10, "id": "pueblo-mexicano", "label": "pueblo-mexicano", "shape": "dot", "font": {"color": "white"}}, {"color": "deepskyblue", "size": 10, "id": "pónganse-trabajar", "label": "pónganse-trabajar", "shape": "dot", "font": {"color": "white"}}, {"color": "deepskyblue", "size": 10, "id": "organismos-internacionales", "label": "organismos-internacionales", "shape": "dot", "font": {"color": "white"}}, {"color": "deepskyblue", "size": 10, "id": "denuncia-persecución", "label": "denuncia-persecución", "shape": "dot", "font": {"color": "white"}}, {"color": "deepskyblue", "size": 10, "id": "delincuentes-cuello", "label": "delincuentes-cuello", "shape": "dot", "font": {"color": "white"}}, {"color": "deepskyblue", "size": 10, "id": "presentó-denuncia", "label": "presentó-denuncia", "shape": "dot", "font": {"color": "white"}}, {"color": "deepskyblue", "size": 10, "id": "nuestro-dinero", "label": "nuestro-dinero", "shape": "dot", "font": {"color": "white"}}, {"color": "deepskyblue", "size": 10, "id": "próximo-gobierno", "label": "próximo-gobierno", "shape": "dot", "font": {"color": "white"}}, {"color": "deepskyblue", "size": 10, "id": "gálvez-santiago", "label": "gálvez-santiago", "shape": "dot", "font": {"color": "white"}}, {"color": "deepskyblue", "size": 10, "id": "cartel-sinaloa", "label": "cartel-sinaloa", "shape": "dot", "font": {"color": "white"}}, {"color": "deepskyblue", "size": 10, "id": "felipe-calderón", "label": "felipe-calderón", "shape": "dot", "font": {"color": "white"}}, {"color": "deepskyblue", "size": 10, "id": "nuestros-impuestos", "label": "nuestros-impuestos", "shape": "dot", "font": {"color": "white"}}, {"color": "deepskyblue", "size": 10, "id": "traición-patria", "label": "traición-patria", "shape": "dot", "font": {"color": "white"}}, {"color": "deepskyblue", "size": 10, "id": "rateros-corruptos", "label": "rateros-corruptos", "shape": "dot", "font": {"color": "white"}}, {"color": "deepskyblue", "size": 10, "id": "sandra-cuevas", "label": "sandra-cuevas", "shape": "dot", "font": {"color": "white"}}, {"color": "brown", "size": 30, "id": "MEX - Clara Brugada - TW", "label": "MEX - Clara Brugada - TW", "shape": "dot", "font": {"color": "white"}}, {"color": "brown", "size": 10, "id": "sierra-catarina", "label": "sierra-catarina", "shape": "dot", "font": {"color": "white"}}, {"color": "brown", "size": 10, "id": "nuestra-ciudad", "label": "nuestra-ciudad", "shape": "dot", "font": {"color": "white"}}, {"color": "brown", "size": 10, "id": "claudia-sheinbaum", "label": "claudia-sheinbaum", "shape": "dot", "font": {"color": "white"}}, {"color": "brown", "size": 10, "id": "alcaldía-iztapalapa", "label": "alcaldía-iztapalapa", "shape": "dot", "font": {"color": "white"}}, {"color": "brown", "size": 10, "id": "grandes-mujeres", "label": "grandes-mujeres", "shape": "dot", "font": {"color": "white"}}, {"color": "brown", "size": 10, "id": "tiempo-mujeres", "label": "tiempo-mujeres", "shape": "dot", "font": {"color": "white"}}, {"color": "brown", "size": 10, "id": "sheinbaum-brugada", "label": "sheinbaum-brugada", "shape": "dot", "font": {"color": "white"}}, {"color": "brown", "size": 10, "id": "solucionar-problema", "label": "solucionar-problema", "shape": "dot", "font": {"color": "white"}}, {"color": "brown", "size": 10, "id": "infraestructura-hidráulica", "label": "infraestructura-hidráulica", "shape": "dot", "font": {"color": "white"}}, {"color": "brown", "size": 10, "id": "cuarta-transformación", "label": "cuarta-transformación", "shape": "dot", "font": {"color": "white"}}, {"color": "brown", "size": 10, "id": "comunidades-indígenas", "label": "comunidades-indígenas", "shape": "dot", "font": {"color": "white"}}, {"color": "brown", "size": 10, "id": "mamando-erario", "label": "mamando-erario", "shape": "dot", "font": {"color": "white"}}, {"color": "brown", "size": 10, "id": "porque-morena", "label": "porque-morena", "shape": "dot", "font": {"color": "white"}}, {"color": "brown", "size": 10, "id": "morena-ciudad", "label": "morena-ciudad", "shape": "dot", "font": {"color": "white"}}, {"color": "brown", "size": 10, "id": "gobierno-ciudad", "label": "gobierno-ciudad", "shape": "dot", "font": {"color": "white"}}, {"color": "brown", "size": 10, "id": "méxico-morena", "label": "méxico-morena", "shape": "dot", "font": {"color": "white"}}, {"color": "brown", "size": 10, "id": "miguel-hidalgo", "label": "miguel-hidalgo", "shape": "dot", "font": {"color": "white"}}, {"color": "brown", "size": 10, "id": "viviendo-erario", "label": "viviendo-erario", "shape": "dot", "font": {"color": "white"}}, {"color": "brown", "size": 10, "id": "contra-morena", "label": "contra-morena", "shape": "dot", "font": {"color": "white"}}, {"color": "brown", "size": 10, "id": "erario-público", "label": "erario-público", "shape": "dot", "font": {"color": "white"}}, {"color": "brown", "size": 10, "id": "secretaria-ambiente", "label": "secretaria-ambiente", "shape": "dot", "font": {"color": "white"}}, {"color": "brown", "size": 10, "id": "clarita-claudia", "label": "clarita-claudia", "shape": "dot", "font": {"color": "white"}}, {"color": "brown", "size": 10, "id": "iztapalapa-brugada", "label": "iztapalapa-brugada", "shape": "dot", "font": {"color": "white"}}], [{"Frecuencia": 8, "value": 0.056338028169014086, "width": 0.056338028169014086, "length": 17.75, "from": "MEX - Salomón Chertorivski - TW", "to": "movimiento-ciudadano"}, {"Frecuencia": 7, "value": 0.04929577464788732, "width": 0.04929577464788732, "length": 20.28571428571429, "from": "MEX - Salomón Chertorivski - TW", "to": "ciudad-méxico"}, {"Frecuencia": 7, "value": 0.04929577464788732, "width": 0.04929577464788732, "length": 20.28571428571429, "from": "MEX - Salomón Chertorivski - TW", "to": "repetición-programa"}, {"Frecuencia": 7, "value": 0.04929577464788732, "width": 0.04929577464788732, "length": 20.28571428571429, "from": "MEX - Salomón Chertorivski - TW", "to": "programa-análisis"}, {"Frecuencia": 7, "value": 0.04929577464788732, "width": 0.04929577464788732, "length": 20.28571428571429, "from": "MEX - Salomón Chertorivski - TW", "to": "análisis-colaboradores"}, {"Frecuencia": 6, "value": 0.04225352112676056, "width": 0.04225352112676056, "length": 23.666666666666668, "from": "MEX - Salomón Chertorivski - TW", "to": "candidato-salomón"}, {"Frecuencia": 5, "value": 0.035211267605633804, "width": 0.035211267605633804, "length": 28.4, "from": "MEX - Salomón Chertorivski - TW", "to": "emergencia-hídrica"}, {"Frecuencia": 4, "value": 0.028169014084507043, "width": 0.028169014084507043, "length": 35.5, "from": "MEX - Salomón Chertorivski - TW", "to": "cartel-inmobiliario"}, {"Frecuencia": 4, "value": 0.028169014084507043, "width": 0.028169014084507043, "length": 35.5, "from": "MEX - Salomón Chertorivski - TW", "to": "continúa-horario"}, {"Frecuencia": 4, "value": 0.028169014084507043, "width": 0.028169014084507043, "length": 35.5, "from": "MEX - Salomón Chertorivski - TW", "to": "horario-repetición"}, {"Frecuencia": 4, "value": 0.028169014084507043, "width": 0.028169014084507043, "length": 35.5, "from": "MEX - Salomón Chertorivski - TW", "to": "colaboradores-entrevistará"}, {"Frecuencia": 4, "value": 0.028169014084507043, "width": 0.028169014084507043, "length": 35.5, "from": "MEX - Salomón Chertorivski - TW", "to": "entrevistará-candidato"}, {"Frecuencia": 4, "value": 0.028169014084507043, "width": 0.028169014084507043, "length": 35.5, "from": "MEX - Salomón Chertorivski - TW", "to": "jefatura-gobierno"}, {"Frecuencia": 3, "value": 0.02112676056338028, "width": 0.02112676056338028, "length": 47.333333333333336, "from": "MEX - Salomón Chertorivski - TW", "to": "salomón-partido"}, {"Frecuencia": 3, "value": 0.02112676056338028, "width": 0.02112676056338028, "length": 47.333333333333336, "from": "MEX - Salomón Chertorivski - TW", "to": "declare-emergencia"}, {"Frecuencia": 3, "value": 0.02112676056338028, "width": 0.02112676056338028, "length": 47.333333333333336, "from": "MEX - Salomón Chertorivski - TW", "to": "muchas-gracias"}, {"Frecuencia": 3, "value": 0.02112676056338028, "width": 0.02112676056338028, "length": 47.333333333333336, "from": "MEX - Salomón Chertorivski - TW", "to": "boletos-cuenta"}, {"Frecuencia": 3, "value": 0.02112676056338028, "width": 0.02112676056338028, "length": 47.333333333333336, "from": "MEX - Salomón Chertorivski - TW", "to": "cuenta-cualquier"}, {"Frecuencia": 3, "value": 0.02112676056338028, "width": 0.02112676056338028, "length": 47.333333333333336, "from": "MEX - Salomón Chertorivski - TW", "to": "cualquier-evento"}, {"Frecuencia": 3, "value": 0.02112676056338028, "width": 0.02112676056338028, "length": 47.333333333333336, "from": "MEX - Salomón Chertorivski - TW", "to": "evento-falsos"}, {"Frecuencia": 3, "value": 0.02112676056338028, "width": 0.02112676056338028, "length": 47.333333333333336, "from": "MEX - Salomón Chertorivski - TW", "to": "falsos-trabaja"}, {"Frecuencia": 3, "value": 0.02112676056338028, "width": 0.02112676056338028, "length": 47.333333333333336, "from": "MEX - Salomón Chertorivski - TW", "to": "trabaja-estudio"}, {"Frecuencia": 3, "value": 0.02112676056338028, "width": 0.02112676056338028, "length": 47.333333333333336, "from": "MEX - Salomón Chertorivski - TW", "to": "estudio-ratero"}, {"Frecuencia": 3, "value": 0.02112676056338028, "width": 0.02112676056338028, "length": 47.333333333333336, "from": "MEX - Salomón Chertorivski - TW", "to": "ratero-estafador"}, {"Frecuencia": 3, "value": 0.02112676056338028, "width": 0.02112676056338028, "length": 47.333333333333336, "from": "MEX - Salomón Chertorivski - TW", "to": "estafador-falsas"}, {"Frecuencia": 3, "value": 0.02112676056338028, "width": 0.02112676056338028, "length": 47.333333333333336, "from": "MEX - Salomón Chertorivski - TW", "to": "chertorivski-advierte"}, {"Frecuencia": 3, "value": 0.02112676056338028, "width": 0.02112676056338028, "length": 47.333333333333336, "from": "MEX - Salomón Chertorivski - TW", "to": "advierte-crisis"}, {"Frecuencia": 2, "value": 0.014084507042253521, "width": 0.014084507042253521, "length": 71.0, "from": "MEX - Salomón Chertorivski - TW", "to": "tenemos-paliza"}, {"Frecuencia": 2, "value": 0.014084507042253521, "width": 0.014084507042253521, "length": 71.0, "from": "MEX - Salomón Chertorivski - TW", "to": "paliza-exterminar"}, {"Frecuencia": 2, "value": 0.014084507042253521, "width": 0.014084507042253521, "length": 71.0, "from": "MEX - Salomón Chertorivski - TW", "to": "exterminar-exterminando"}, {"Frecuencia": 24, "value": 0.16901408450704225, "width": 0.16901408450704225, "length": 5.916666666666667, "from": "ciudad-méxico", "to": "MEX - Santiago Taboada - TW"}, {"Frecuencia": 33, "value": 0.2323943661971831, "width": 0.2323943661971831, "length": 4.303030303030303, "from": "ciudad-méxico", "to": "MEX - Clara Brugada - TW"}, {"Frecuencia": 142, "value": 1.0, "width": 1.0, "length": 1.0, "from": "cartel-inmobiliario", "to": "MEX - Santiago Taboada - TW"}, {"Frecuencia": 10, "value": 0.07042253521126761, "width": 0.07042253521126761, "length": 14.2, "from": "cartel-inmobiliario", "to": "MEX - Clara Brugada - TW"}, {"Frecuencia": 21, "value": 0.14788732394366197, "width": 0.14788732394366197, "length": 6.761904761904762, "from": "jefatura-gobierno", "to": "MEX - Santiago Taboada - TW"}, {"Frecuencia": 12, "value": 0.08450704225352113, "width": 0.08450704225352113, "length": 11.833333333333334, "from": "jefatura-gobierno", "to": "MEX - Clara Brugada - TW"}, {"Frecuencia": 112, "value": 0.7887323943661971, "width": 0.7887323943661971, "length": 1.267857142857143, "from": "MEX - Santiago Taboada - TW", "to": "santiago-taboada"}, {"Frecuencia": 57, "value": 0.4014084507042254, "width": 0.4014084507042254, "length": 2.4912280701754383, "from": "MEX - Santiago Taboada - TW", "to": "persecución-política"}, {"Frecuencia": 49, "value": 0.34507042253521125, "width": 0.34507042253521125, "length": 2.8979591836734695, "from": "MEX - Santiago Taboada - TW", "to": "cártel-inmobiliario"}, {"Frecuencia": 39, "value": 0.2746478873239437, "width": 0.2746478873239437, "length": 3.6410256410256405, "from": "MEX - Santiago Taboada - TW", "to": "estados-unidos"}, {"Frecuencia": 33, "value": 0.2323943661971831, "width": 0.2323943661971831, "length": 4.303030303030303, "from": "MEX - Santiago Taboada - TW", "to": "elección-estado"}, {"Frecuencia": 26, "value": 0.18309859154929578, "width": 0.18309859154929578, "length": 5.461538461538462, "from": "MEX - Santiago Taboada - TW", "to": "traidores-patria"}, {"Frecuencia": 21, "value": 0.14788732394366197, "width": 0.14788732394366197, "length": 6.761904761904762, "from": "MEX - Santiago Taboada - TW", "to": "benito-juárez"}, {"Frecuencia": 16, "value": 0.11267605633802817, "width": 0.11267605633802817, "length": 8.875, "from": "MEX - Santiago Taboada - TW", "to": "cuello-blanco"}, {"Frecuencia": 15, "value": 0.1056338028169014, "width": 0.1056338028169014, "length": 9.466666666666667, "from": "MEX - Santiago Taboada - TW", "to": "perseguidos-políticos"}, {"Frecuencia": 14, "value": 0.09859154929577464, "width": 0.09859154929577464, "length": 10.142857142857144, "from": "MEX - Santiago Taboada - TW", "to": "pueblo-méxico"}, {"Frecuencia": 13, "value": 0.09154929577464789, "width": 0.09154929577464789, "length": 10.923076923076923, "from": "MEX - Santiago Taboada - TW", "to": "perseguido-político"}, {"Frecuencia": 12, "value": 0.08450704225352113, "width": 0.08450704225352113, "length": 11.833333333333334, "from": "MEX - Santiago Taboada - TW", "to": "xóchitl-gálvez"}, {"Frecuencia": 10, "value": 0.07042253521126761, "width": 0.07042253521126761, "length": 14.2, "from": "MEX - Santiago Taboada - TW", "to": "pueblo-mexicano"}, {"Frecuencia": 10, "value": 0.07042253521126761, "width": 0.07042253521126761, "length": 14.2, "from": "MEX - Santiago Taboada - TW", "to": "pónganse-trabajar"}, {"Frecuencia": 8, "value": 0.056338028169014086, "width": 0.056338028169014086, "length": 17.75, "from": "MEX - Santiago Taboada - TW", "to": "organismos-internacionales"}, {"Frecuencia": 8, "value": 0.056338028169014086, "width": 0.056338028169014086, "length": 17.75, "from": "MEX - Santiago Taboada - TW", "to": "denuncia-persecución"}, {"Frecuencia": 8, "value": 0.056338028169014086, "width": 0.056338028169014086, "length": 17.75, "from": "MEX - Santiago Taboada - TW", "to": "delincuentes-cuello"}, {"Frecuencia": 7, "value": 0.04929577464788732, "width": 0.04929577464788732, "length": 20.28571428571429, "from": "MEX - Santiago Taboada - TW", "to": "presentó-denuncia"}, {"Frecuencia": 7, "value": 0.04929577464788732, "width": 0.04929577464788732, "length": 20.28571428571429, "from": "MEX - Santiago Taboada - TW", "to": "nuestro-dinero"}, {"Frecuencia": 7, "value": 0.04929577464788732, "width": 0.04929577464788732, "length": 20.28571428571429, "from": "MEX - Santiago Taboada - TW", "to": "próximo-gobierno"}, {"Frecuencia": 7, "value": 0.04929577464788732, "width": 0.04929577464788732, "length": 20.28571428571429, "from": "MEX - Santiago Taboada - TW", "to": "gálvez-santiago"}, {"Frecuencia": 7, "value": 0.04929577464788732, "width": 0.04929577464788732, "length": 20.28571428571429, "from": "MEX - Santiago Taboada - TW", "to": "cartel-sinaloa"}, {"Frecuencia": 7, "value": 0.04929577464788732, "width": 0.04929577464788732, "length": 20.28571428571429, "from": "MEX - Santiago Taboada - TW", "to": "felipe-calderón"}, {"Frecuencia": 7, "value": 0.04929577464788732, "width": 0.04929577464788732, "length": 20.28571428571429, "from": "MEX - Santiago Taboada - TW", "to": "nuestros-impuestos"}, {"Frecuencia": 7, "value": 0.04929577464788732, "width": 0.04929577464788732, "length": 20.28571428571429, "from": "MEX - Santiago Taboada - TW", "to": "traición-patria"}, {"Frecuencia": 7, "value": 0.04929577464788732, "width": 0.04929577464788732, "length": 20.28571428571429, "from": "MEX - Santiago Taboada - TW", "to": "rateros-corruptos"}, {"Frecuencia": 6, "value": 0.04225352112676056, "width": 0.04225352112676056, "length": 23.666666666666668, "from": "MEX - Santiago Taboada - TW", "to": "sandra-cuevas"}, {"Frecuencia": 4, "value": 0.028169014084507043, "width": 0.028169014084507043, "length": 35.5, "from": "santiago-taboada", "to": "MEX - Clara Brugada - TW"}, {"Frecuencia": 4, "value": 0.028169014084507043, "width": 0.028169014084507043, "length": 35.5, "from": "cártel-inmobiliario", "to": "MEX - Clara Brugada - TW"}, {"Frecuencia": 4, "value": 0.028169014084507043, "width": 0.028169014084507043, "length": 35.5, "from": "estados-unidos", "to": "MEX - Clara Brugada - TW"}, {"Frecuencia": 4, "value": 0.028169014084507043, "width": 0.028169014084507043, "length": 35.5, "from": "benito-juárez", "to": "MEX - Clara Brugada - TW"}, {"Frecuencia": 10, "value": 0.07042253521126761, "width": 0.07042253521126761, "length": 14.2, "from": "MEX - Clara Brugada - TW", "to": "sierra-catarina"}, {"Frecuencia": 8, "value": 0.056338028169014086, "width": 0.056338028169014086, "length": 17.75, "from": "MEX - Clara Brugada - TW", "to": "nuestra-ciudad"}, {"Frecuencia": 7, "value": 0.04929577464788732, "width": 0.04929577464788732, "length": 20.28571428571429, "from": "MEX - Clara Brugada - TW", "to": "claudia-sheinbaum"}, {"Frecuencia": 6, "value": 0.04225352112676056, "width": 0.04225352112676056, "length": 23.666666666666668, "from": "MEX - Clara Brugada - TW", "to": "alcaldía-iztapalapa"}, {"Frecuencia": 6, "value": 0.04225352112676056, "width": 0.04225352112676056, "length": 23.666666666666668, "from": "MEX - Clara Brugada - TW", "to": "grandes-mujeres"}, {"Frecuencia": 5, "value": 0.035211267605633804, "width": 0.035211267605633804, "length": 28.4, "from": "MEX - Clara Brugada - TW", "to": "tiempo-mujeres"}, {"Frecuencia": 5, "value": 0.035211267605633804, "width": 0.035211267605633804, "length": 28.4, "from": "MEX - Clara Brugada - TW", "to": "sheinbaum-brugada"}, {"Frecuencia": 5, "value": 0.035211267605633804, "width": 0.035211267605633804, "length": 28.4, "from": "MEX - Clara Brugada - TW", "to": "solucionar-problema"}, {"Frecuencia": 5, "value": 0.035211267605633804, "width": 0.035211267605633804, "length": 28.4, "from": "MEX - Clara Brugada - TW", "to": "infraestructura-hidráulica"}, {"Frecuencia": 4, "value": 0.028169014084507043, "width": 0.028169014084507043, "length": 35.5, "from": "MEX - Clara Brugada - TW", "to": "cuarta-transformación"}, {"Frecuencia": 4, "value": 0.028169014084507043, "width": 0.028169014084507043, "length": 35.5, "from": "MEX - Clara Brugada - TW", "to": "comunidades-indígenas"}, {"Frecuencia": 4, "value": 0.028169014084507043, "width": 0.028169014084507043, "length": 35.5, "from": "MEX - Clara Brugada - TW", "to": "mamando-erario"}, {"Frecuencia": 4, "value": 0.028169014084507043, "width": 0.028169014084507043, "length": 35.5, "from": "MEX - Clara Brugada - TW", "to": "porque-morena"}, {"Frecuencia": 4, "value": 0.028169014084507043, "width": 0.028169014084507043, "length": 35.5, "from": "MEX - Clara Brugada - TW", "to": "morena-ciudad"}, {"Frecuencia": 4, "value": 0.028169014084507043, "width": 0.028169014084507043, "length": 35.5, "from": "MEX - Clara Brugada - TW", "to": "gobierno-ciudad"}, {"Frecuencia": 4, "value": 0.028169014084507043, "width": 0.028169014084507043, "length": 35.5, "from": "MEX - Clara Brugada - TW", "to": "méxico-morena"}, {"Frecuencia": 4, "value": 0.028169014084507043, "width": 0.028169014084507043, "length": 35.5, "from": "MEX - Clara Brugada - TW", "to": "miguel-hidalgo"}, {"Frecuencia": 4, "value": 0.028169014084507043, "width": 0.028169014084507043, "length": 35.5, "from": "MEX - Clara Brugada - TW", "to": "viviendo-erario"}, {"Frecuencia": 4, "value": 0.028169014084507043, "width": 0.028169014084507043, "length": 35.5, "from": "MEX - Clara Brugada - TW", "to": "contra-morena"}, {"Frecuencia": 4, "value": 0.028169014084507043, "width": 0.028169014084507043, "length": 35.5, "from": "MEX - Clara Brugada - TW", "to": "erario-público"}, {"Frecuencia": 4, "value": 0.028169014084507043, "width": 0.028169014084507043, "length": 35.5, "from": "MEX - Clara Brugada - TW", "to": "secretaria-ambiente"}, {"Frecuencia": 4, "value": 0.028169014084507043, "width": 0.028169014084507043, "length": 35.5, "from": "MEX - Clara Brugada - TW", "to": "clarita-claudia"}, {"Frecuencia": 3, "value": 0.02112676056338028, "width": 0.02112676056338028, "length": 47.333333333333336, "from": "MEX - Clara Brugada - TW", "to": "iztapalapa-brugada"}]]}