{"2024-02-13-2024-02-13": [{"Influencer": "PartidoMorenaMx", "Centralidad": 63.43}, {"Influencer": "XochitlGalvez", "Centralidad": 9.96}, {"Influencer": "Xochitl2024", "Centralidad": 9.81}, {"Influencer": "AccionNacional", "Centralidad": 9.44}, {"Influencer": "lopezobrador_", "Centralidad": 8.98}, {"Influencer": "mario_delgado", "Centralidad": 8.41}, {"Influencer": "Claudiashein", "Centralidad": 7.91}, {"Influencer": "PRI_Nacional", "Centralidad": 7.56}, {"Influencer": "alitomorenoc", "Centralidad": 7.37}, {"Influencer": "PRDMexico", "Centralidad": 6.17}, {"Influencer": "JTrianaT", "Centralidad": 6.07}, {"Influencer": "Alonsotamez", "Centralidad": 5.83}, {"Influencer": "caroviggiano", "Centralidad": 5.83}, {"Influencer": "rubenmoreiravdz", "Centralidad": 5.83}, {"Influencer": "JorgeLara1", "Centralidad": 5.65}], "2024-02-14-2024-02-14": [{"Influencer": "STaboadaMx", "Centralidad": 44.58}, {"Influencer": "XochitlGalvez", "Centralidad": 28.86}, {"Influencer": "JTrianaT", "Centralidad": 26.77}, {"Influencer": "kenialopezr", "Centralidad": 24.43}, {"Influencer": "marioraphaelc", "Centralidad": 22.72}, {"Influencer": "PartidoMorenaMx", "Centralidad": 12.75}, {"Influencer": "aeibrahmrl", "Centralidad": 4.7}, {"Influencer": "linaswcdmx", "Centralidad": 4.7}, {"Influencer": "cokegilmour", "Centralidad": 4.62}, {"Influencer": "PulpChupeteador", "Centralidad": 4.49}, {"Influencer": "necrophanto", "Centralidad": 4.49}, {"Influencer": "EmmaVanellope", "Centralidad": 4.48}, {"Influencer": "Alexand95463483", "Centralidad": 4.46}, {"Influencer": "avestruzeterea", "Centralidad": 4.46}, {"Influencer": "mujeresalborde", "Centralidad": 4.43}], "2024-02-15-2024-02-15": [{"Influencer": "ClaraBrugadaM", "Centralidad": 57.35}, {"Influencer": "iecm", "Centralidad": 34.55}, {"Influencer": "MorenaCiudadMex", "Centralidad": 11.46}, {"Influencer": "VerdeCDMX", "Centralidad": 8.69}, {"Influencer": "PTCDMX_oficial", "Centralidad": 8.69}, {"Influencer": "PartidoMorenaMx", "Centralidad": 6.27}, {"Influencer": "Sebas_RM", "Centralidad": 5.94}, {"Influencer": "mario_delgado", "Centralidad": 5.63}, {"Influencer": "STaboadaMx", "Centralidad": 4.56}, {"Influencer": "RINT0RIN0", "Centralidad": 4.5}, {"Influencer": "MarcelaH45432", "Centralidad": 4.3}, {"Influencer": "MartnAntonioRa5", "Centralidad": 4.3}, {"Influencer": "Fanyeas", "Centralidad": 4.3}, {"Influencer": "ErikaUgalde14", "Centralidad": 4.3}, {"Influencer": "JavierTole88289", "Centralidad": 4.3}], "2024-02-16-2024-02-16": [{"Influencer": "STaboadaMx", "Centralidad": 43.75}, {"Influencer": "ClaraBrugadaM", "Centralidad": 41.95}, {"Influencer": "GabyCuevas", "Centralidad": 16.74}, {"Influencer": "iecdmx", "Centralidad": 16.25}, {"Influencer": "FreddyOliviery", "Centralidad": 12.53}, {"Influencer": "XochitlGalvez", "Centralidad": 11.91}, {"Influencer": "PartidoMorenaMx", "Centralidad": 7.09}, {"Influencer": "MorenaCiudadMex", "Centralidad": 6.82}, {"Influencer": "VerdeCDMX", "Centralidad": 6.75}, {"Influencer": "iecm", "Centralidad": 6.7}, {"Influencer": "PTCDMX_oficial", "Centralidad": 6.59}, {"Influencer": "CitlaHM", "Centralidad": 6.1}, {"Influencer": "mario_delgado", "Centralidad": 6.09}, {"Influencer": "Sebas_RM", "Centralidad": 5.25}, {"Influencer": "julioc_moreno", "Centralidad": 4.47}], "2024-02-17-2024-02-17": [{"Influencer": "ClaraBrugadaM", "Centralidad": 57.61}, {"Influencer": "Claudiashein", "Centralidad": 37.97}, {"Influencer": "STaboadaMx", "Centralidad": 10.18}, {"Influencer": "El_Enigma", "Centralidad": 5.23}, {"Influencer": "subLuis", "Centralidad": 5.04}, {"Influencer": "Guadalu41297779", "Centralidad": 5.04}, {"Influencer": "ngela_milius", "Centralidad": 5.04}, {"Influencer": "Ricardo25934049", "Centralidad": 4.95}, {"Influencer": "Amsterdam269", "Centralidad": 4.91}, {"Influencer": "todr59", "Centralidad": 4.91}, {"Influencer": "RicarAmelia", "Centralidad": 4.86}, {"Influencer": "IrisDeTeli", "Centralidad": 4.75}, {"Influencer": "OctavioFloresA7", "Centralidad": 4.74}, {"Influencer": "PSepultur", "Centralidad": 4.74}, {"Influencer": "FifiMercenario", "Centralidad": 4.74}], "2024-02-18-2024-02-18": [{"Influencer": "STaboadaMx", "Centralidad": 35.29}, {"Influencer": "MiguelPenaflor", "Centralidad": 21.9}, {"Influencer": "lopezobrador_", "Centralidad": 18.05}, {"Influencer": "SocCivilMx", "Centralidad": 17.26}, {"Influencer": "ferbelaunzaran", "Centralidad": 17.02}, {"Influencer": "ClaudioXGG", "Centralidad": 16.96}, {"Influencer": "redesunidosmx", "Centralidad": 16.93}, {"Influencer": "FCN_mx", "Centralidad": 16.93}, {"Influencer": "JTrianaT", "Centralidad": 16.88}, {"Influencer": "analucia_medina", "Centralidad": 16.87}, {"Influencer": "acostanaranjo", "Centralidad": 16.79}, {"Influencer": "luisantgarcia", "Centralidad": 16.52}, {"Influencer": "marianagc", "Centralidad": 7.75}, {"Influencer": "MomoSosa", "Centralidad": 7.7}, {"Influencer": "AndritoOs", "Centralidad": 7.05}], "2024-02-19-2024-02-19": [{"Influencer": "STaboadaMx", "Centralidad": 33.04}, {"Influencer": "EmilioAlvarezI", "Centralidad": 19.72}, {"Influencer": "MeDicenRub", "Centralidad": 19.72}, {"Influencer": "marianagc", "Centralidad": 19.51}, {"Influencer": "JorgeRoHe", "Centralidad": 19.46}, {"Influencer": "Dario_7070", "Centralidad": 19.39}, {"Influencer": "Maaresqui", "Centralidad": 19.39}, {"Influencer": "PAN_CDMX", "Centralidad": 19.28}, {"Influencer": "laualvarez_80", "Centralidad": 19.19}, {"Influencer": "PANistasXMx", "Centralidad": 19.19}, {"Influencer": "mexicanxsaccion", "Centralidad": 19.19}, {"Influencer": "blades_omar", "Centralidad": 8.93}, {"Influencer": "OrtegoTereso", "Centralidad": 8.77}, {"Influencer": "Luchoyolo", "Centralidad": 8.73}, {"Influencer": "sergemex1985", "Centralidad": 8.66}]}